endstone_stubgen/__init__.py
endstone_stubgen/extensions.py
endstone_stubgen/py.typed
endstone_stubgen/templates/alias.jinja
endstone_stubgen/templates/attribute.jinja
endstone_stubgen/templates/class.jinja
endstone_stubgen/templates/docstring.jinja
endstone_stubgen/templates/function.jinja
endstone_stubgen/templates/module.jinja
endstone_stubgen/templates/property.jinja
endstone_stubgen-0.1.0.dist-info/WHEEL
endstone_stubgen-0.1.0.dist-info/entry_points.txt
endstone_stubgen-0.1.0.dist-info/METADATA
endstone_stubgen-0.1.0.dist-info/RECORD
