Metadata-Version: 2.4
Name: endstone-stubgen
Version: 0.1.0
Summary: The next-generation stub generator for pybind11 modules, built with Griffe and Jinja2
Keywords: stubs,pybind11,type-hints,pyi,stub-generator,griffe
Author: Vincent
Author-email: Vincent <magicdroidx@gmail.com>
License-Expression: MIT
Classifier: Development Status :: 4 - Beta
Classifier: Intended Audience :: Developers
Classifier: License :: OSI Approved :: MIT License
Classifier: Programming Language :: Python :: 3
Classifier: Programming Language :: Python :: 3.11
Classifier: Programming Language :: Python :: 3.12
Classifier: Programming Language :: Python :: 3.13
Classifier: Topic :: Software Development :: Code Generators
Classifier: Typing :: Typed
Requires-Dist: jinja2
Requires-Dist: griffe
Requires-Python: >=3.11
Project-URL: Homepage, https://github.com/EndstoneMC/stubgen
Project-URL: Issues, https://github.com/EndstoneMC/stubgen/issues
Project-URL: Repository, https://github.com/EndstoneMC/stubgen
